<oai_dc:dc xmlns:oai_dc="http://www.openarchives.org/OAI/2.0/oai_dc/" xmlns:dc="http://purl.org/dc/elements/1.1/" xmlns:xsi="http://www.w3.org/2001/XMLSchema-instance" xsi:schemaLocation="http://www.openarchives.org/OAI/2.0/oai_dc/ http://www.openarchives.org/OAI/2.0/oai_dc.xsd">
  <dc:title>Bilan des connaissances acquises sur la faune et la flore sous-marines de la région de Djibouti</dc:title>
  <dc:creator>Abbes, Rene</dc:creator>
  <dc:description>Les connaissances que l'IFREMER a pu acquérir sur la flore et la faune sous-marines du secteur de Djibouti remontent, pour une grande partie d'entre-elles, aux années 1973/1974. En effet, à cette époque l'ISTPM avait été sollicité par les autorités locales pour évaluer les possibilités de développement de la pêche dans la région. Dans ce but un programme de recherches appliquées avait été élaboré ; il portait sur les points suivants : - inventaire et répartition spatio-temporelle des espèces d'intérêt commercial ; - étude de la distribution et du comportement des principales espèces en fonction des variations des conditions physico-chimiques, du milieu ; - expérimentation d'engins de pêche adéquats et estimation de leurs rendements. Ces actions ont été conduites à partir de 1973 par une équipe de chercheurs et techniciens de l'ISTPM à l'aide du navire "TADJOURAH" spécialement aménagé pour la circonstance.</dc:description>
  <dc:date>1985</dc:date>
  <dc:type>text</dc:type>
  <dc:type>Report</dc:type>
  <dc:format>application/pdf</dc:format>
  <dc:identifier>http://archimer.ifremer.fr/doc/00046/15677/13080.pdf</dc:identifier>
  <dc:language>fr</dc:language>
  <dc:relation>http://archimer.ifremer.fr/doc/00046/15677/</dc:relation>
</oai_dc:dc>