<oai_dc:dc xmlns:oai_dc="http://www.openarchives.org/OAI/2.0/oai_dc/" xmlns:dc="http://purl.org/dc/elements/1.1/" xmlns:xsi="http://www.w3.org/2001/XMLSchema-instance" xsi:schemaLocation="http://www.openarchives.org/OAI/2.0/oai_dc/ http://www.openarchives.org/OAI/2.0/oai_dc.xsd">
  <dc:title>Méthodes usuelles d'analyse bacteriologique pour le contrôle sanitaire courant des eaux de mer et des coquillages</dc:title>
  <dc:creator>Mazieres, Jean</dc:creator>
  <dc:description>Le contrôle sanitaire des eaux de mer et des coquillages a pour but de garantir aux consommateurs des produits sans risque pour leur santé.Sont à redouter les germes pathogènes qui se transmettent par voie hydrique tels que les salmonelles (fièvres typhoîdes), les shigelles (dysenteries), les vibrions (choléra) et certains virus comme ceux responsables des hépatites infectieuses. La presence d'organismes pathogènes constituent une preuve convaincante d'une pollution dangereuse, mais leur nombre est souvent limité dans le milieu et leur mise en évidence difficile à cause de la durée, du coût et parfois de l'insuffisance des techniques d'analyses actuelles. De plus, si on fait de leur présence le critère de refus de mise à la consommation des denrées éminemment périssables comme les coquillages, on risque de voir consommer celles-ci avant qu'un diagnostic soit fait et que des mesures prophylactiques soient prises.</dc:description>
  <dc:date>1981</dc:date>
  <dc:type>text</dc:type>
  <dc:type>Report</dc:type>
  <dc:format>application/pdf</dc:format>
  <dc:identifier>http://archimer.ifremer.fr/doc/00045/15608/13012.pdf</dc:identifier>
  <dc:language>fr</dc:language>
  <dc:relation>http://archimer.ifremer.fr/doc/00045/15608/</dc:relation>
</oai_dc:dc>